<?xml version="1.0" encoding="UTF-8"?>
<SunopsisExport>
<Admin RepositoryVersion="05.02.02.05" IsLegacyIdCompatible="false" />
<Encryption algorithm="AES" keyLength="128" exportKeyHash="" keyVect="edx7eqW6nSQqJd+3cageBg==" exportKeySalt="996db495-94eb-49aa-81d2-1d26d3abeb41" containsCipherText="false"/>
<Object class="com.sunopsis.dwg.dbobj.SnpModFolder">
		<Field name="ExtVersion" type="java.lang.String">null</Field>
	<Field name="FirstDate" type="java.sql.Timestamp"><![CDATA[2017-01-13 10:04:13.0]]></Field>
	<Field name="FirstUser" type="java.lang.String"><![CDATA[SUPERVISOR]]></Field>
	<Field name="GlobalId" type="java.lang.String"><![CDATA[8e7a0e0f-e30b-4f6b-8a09-b574198b9442]]></Field>
	<Field name="IndChange" type="java.lang.String"><![CDATA[U]]></Field>
	<Field name="IntVersion" type="com.sunopsis.sql.DbInt"><![CDATA[1]]></Field>
	<Field name="IModFolder" type="com.sunopsis.sql.DbInt"><![CDATA[11]]></Field>
	<Field name="ITxtDescription" type="com.sunopsis.sql.DbInt"><![CDATA[null]]></Field>
	<Field name="LastDate" type="java.sql.Timestamp"><![CDATA[2017-01-13 10:25:27.0]]></Field>
	<Field name="LastUser" type="java.lang.String"><![CDATA[SUPERVISOR]]></Field>
	<Field name="ModFolderName" type="java.lang.String"><![CDATA[MJR_Pruebas]]></Field>
	<Field name="ParIModFolder" type="com.sunopsis.sql.DbInt"><![CDATA[null]]></Field>
	<Field name="VLastDate" type="java.sql.Timestamp">null</Field>
</Object>
<Object class="com.sunopsis.dwg.dbobj.SnpChildFCO">
		<Field name="Type" type="java.lang.String"><![CDATA[SnpModel]]></Field>
	<Field name="SubType" type="java.lang.String">null</Field>
	<Field name="Name" type="java.lang.String"><![CDATA[Carpeta_ORACLE]]></Field>
	<Field name="GlobalId" type="java.lang.String"><![CDATA[ad253f80-434e-4011-ba0e-d2628cb94d3a]]></Field>
	<Field name="Version" type="java.lang.String"><![CDATA[4a44a65762965366e8e90a66a8b415a1184eaf63]]></Field>
	<Field name="Path" type="java.lang.String"><![CDATA[Carpeta_ORACLE/MOD_Carpeta_ORACLE.xml]]></Field>
</Object>
<Object class="com.sunopsis.dwg.dbobj.SnpChildFCO">
		<Field name="Type" type="java.lang.String"><![CDATA[SnpModel]]></Field>
	<Field name="SubType" type="java.lang.String">null</Field>
	<Field name="Name" type="java.lang.String"><![CDATA[Base_ORACLE]]></Field>
	<Field name="GlobalId" type="java.lang.String"><![CDATA[10b50111-1cf7-4540-ae2b-211df20f1e18]]></Field>
	<Field name="Version" type="java.lang.String"><![CDATA[28a0bacda59a2d0132c94808dea2b3514d20007c]]></Field>
	<Field name="Path" type="java.lang.String"><![CDATA[Base_ORACLE/MOD_Base_ORACLE.xml]]></Field>
</Object>
<Object class="com.sunopsis.dwg.DwgExportSummary">
		<Field name="ExpTxtNb" type="com.sunopsis.sql.DbInt"><![CDATA[0]]></Field>
	<Field name="InstObjNb" type="com.sunopsis.sql.DbInt"><![CDATA[0]]></Field>
	<Field name="JoinColNb" type="com.sunopsis.sql.DbInt"><![CDATA[0]]></Field>
	<Field name="JoinNb" type="com.sunopsis.sql.DbInt"><![CDATA[0]]></Field>
	<Field name="KeyColNb" type="com.sunopsis.sql.DbInt"><![CDATA[0]]></Field>
	<Field name="KeyNb" type="com.sunopsis.sql.DbInt"><![CDATA[0]]></Field>
	<Field name="LinkDiagNb" type="com.sunopsis.sql.DbInt"><![CDATA[0]]></Field>
	<Field name="MorigTxtNb" type="com.sunopsis.sql.DbInt"><![CDATA[0]]></Field>
	<Field name="MtxtNb" type="com.sunopsis.sql.DbInt"><![CDATA[0]]></Field>
	<Field name="OrigTxtNb" type="com.sunopsis.sql.DbInt"><![CDATA[0]]></Field>
	<Field name="OtherObjectsNb" type="com.sunopsis.sql.DbInt"><![CDATA[1]]></Field>
	<Field name="PlanAgentNb" type="com.sunopsis.sql.DbInt"><![CDATA[0]]></Field>
	<Field name="StepNb" type="com.sunopsis.sql.DbInt"><![CDATA[0]]></Field>
	<Field name="TxtNb" type="com.sunopsis.sql.DbInt"><![CDATA[0]]></Field>
	<Field name="UeOrigNb" type="com.sunopsis.sql.DbInt"><![CDATA[0]]></Field>
	<Field name="UeUsedNb" type="com.sunopsis.sql.DbInt"><![CDATA[0]]></Field>
	<Field name="VarPlanAgentNb" type="com.sunopsis.sql.DbInt"><![CDATA[0]]></Field>
	<Field name="ScenTxtNb" type="com.sunopsis.sql.DbInt"><![CDATA[0]]></Field>
	<Field name="OdiVersion" type="java.lang.String"><![CDATA[12.2.1]]></Field>
	<Field name="OriginRepositoryID" type="com.sunopsis.sql.DbInt"><![CDATA[1]]></Field>
	<Field name="RepositoryVersion" type="java.lang.String"><![CDATA[05.02.02.05]]></Field>
</Object>
</SunopsisExport>
